ip_adapter/__init__.py
ip_adapter/attention_processor.py
ip_adapter/attention_processor_faceid.py
ip_adapter/custom_pipelines.py
ip_adapter/ip_adapter.py
ip_adapter/ip_adapter_faceid.py
ip_adapter/ip_adapter_faceid_separate.py
ip_adapter/resampler.py
ip_adapter/test_resampler.py
ip_adapter/utils.py
ip_adapterv-0.1.0.dist-info/LICENSE
ip_adapterv-0.1.0.dist-info/METADATA
ip_adapterv-0.1.0.dist-info/WHEEL
ip_adapterv-0.1.0.dist-info/RECORD
