Metadata-Version: 2.1
Name: ip-adapterv
Version: 0.1.0
Summary: IP-Adapter: Text Compatible Image Prompt Adapter for Text-to-Image Diffusion Models
License: Apache-2.0
Author: Ye, Hu
Requires-Python: >=3.6
Classifier: License :: OSI Approved :: Apache Software License
Classifier: Programming Language :: Python :: 3
Classifier: Programming Language :: Python :: 3.6
Classifier: Programming Language :: Python :: 3.7
Classifier: Programming Language :: Python :: 3.8
Classifier: Programming Language :: Python :: 3.9
Classifier: Programming Language :: Python :: 3.10
Classifier: Programming Language :: Python :: 3.11
Classifier: Programming Language :: Python :: 3.12
